Workbook

Sheet Company bottom up beta estimate
A1: Bottom up unlevered beta
A2: Business | B2: Revenues | C2: EV/Sales | D2: Estimated value | E2: Weights | F2: Pure play beta | G2: Weight* Beta
A3: Apparel | B3: 12056 | C3: =IF(B3=0," ",VLOOKUP(A3,'US industry averages'!$A$2:$I$96,9)) -> 1.1592906 | D3: =IF(B3=0," ",B3*C3) -> 13976.408 | E3: =IF(B3=0," ",D3/$D$21) -> 0.13624275 | F3: =IF(B3=0," ",VLOOKUP(A3,'US industry averages'!$A$2:$I$95,8)) -> 1.0163797 | G3: =IF(B3=0," ",E3*F3) -> 0.13847437
A4: Building Materials | B4: 17090 | C4: =IF(B4=0," ",VLOOKUP(A4,'US industry averages'!$A$2:$I$95,9)) -> 1.3599831 | D4: =IF(B4=0," ",B4*C4) -> 23242.111 | E4: =IF(B4=0," ",D4/$D$21) -> 0.22656532 | F4: =IF(B4=0," ",VLOOKUP(A4,'US industry averages'!$A$2:$I$95,8)) -> 1.0983593 | G4: =IF(B4=0," ",E4*F4) -> 0.24885012
A5: Machinery | B5: 13964 | C5: =IF(B5=0," ",VLOOKUP(A5,'US industry averages'!$A$2:$I$95,9)) -> 2.6683702 | D5: =IF(B5=0," ",B5*C5) -> 37261.122 | E5: =IF(B5=0," ",D5/$D$21) -> 0.36322337 | F5: =IF(B5=0," ",VLOOKUP(A5,'US industry averages'!$A$2:$I$95,8)) -> 1.0938251 | G5: =IF(B5=0," ",E5*F5) -> 0.39730283
A6: Aerospace/Defense | B6: 8334 | C6: =IF(B6=0," ",VLOOKUP(A6,'US industry averages'!$A$2:$I$95,9)) -> 2.5451076 | D6: =IF(B6=0," ",B6*C6) -> 21210.927 | E6: =IF(B6=0," ",D6/$D$21) -> 0.20676522 | F6: =IF(B6=0," ",VLOOKUP(A6,'US industry averages'!$A$2:$I$95,8)) -> 1.2292962 | G6: =IF(B6=0," ",E6*F6) -> 0.25417571
A7: Air Transport | B7: 6791 | C7: =IF(B7=0," ",VLOOKUP(A7,'US industry averages'!$A$2:$I$95,9)) -> 1.0151711 | D7: =IF(B7=0," ",B7*C7) -> 6894.0266 | E7: =IF(B7=0," ",D7/$D$21) -> 0.067203333 | F7: =IF(B7=0," ",VLOOKUP(A7,'US industry averages'!$A$2:$I$95,8)) -> 0.693998 | G7: =IF(B7=0," ",E7*F7) -> 0.046638979
C8: =IF(B8=0," ",VLOOKUP(A8,'US industry averages'!$A$2:$I$95,9)) | D8: =IF(B8=0," ",B8*C8) | E8: =IF(B8=0," ",D8/$D$21) | F8: =IF(B8=0," ",VLOOKUP(A8,'US industry averages'!$A$2:$I$95,8)) | G8: =IF(B8=0," ",E8*F8)
C9: =IF(B9=0," ",VLOOKUP(A9,'US industry averages'!$A$2:$I$95,9)) | D9: =IF(B9=0," ",B9*C9) | E9: =IF(B9=0," ",D9/$D$21) | F9: =IF(B9=0," ",VLOOKUP(A9,'US industry averages'!$A$2:$I$95,8)) | G9: =IF(B9=0," ",E9*F9)
C10: =IF(B10=0," ",VLOOKUP(A10,'US industry averages'!$A$2:$I$95,9)) | D10: =IF(B10=0," ",B10*C10) | E10: =IF(B10=0," ",D10/$D$21) | F10: =IF(B10=0," ",VLOOKUP(A10,'US industry averages'!$A$2:$I$95,8)) | G10: =IF(B10=0," ",E10*F10)
C11: =IF(B11=0," ",VLOOKUP(A11,'US industry averages'!$A$2:$I$95,9)) | D11: =IF(B11=0," ",B11*C11) | E11: =IF(B11=0," ",D11/$D$21) | F11: =IF(B11=0," ",VLOOKUP(A11,'US industry averages'!$A$2:$I$95,8)) | G11: =IF(B11=0," ",E11*F11)
C12: =IF(B12=0," ",VLOOKUP(A12,'US industry averages'!$A$2:$I$95,9)) | D12: =IF(B12=0," ",B12*C12) | E12: =IF(B12=0," ",D12/$D$21) | F12: =IF(B12=0," ",VLOOKUP(A12,'US industry averages'!$A$2:$I$95,8)) | G12: =IF(B12=0," ",E12*F12)
C13: =IF(B13=0," ",VLOOKUP(A13,'US industry averages'!$A$2:$I$95,9)) | D13: =IF(B13=0," ",B13*C13) | E13: =IF(B13=0," ",D13/$D$21) | F13: =IF(B13=0," ",VLOOKUP(A13,'US industry averages'!$A$2:$I$95,8)) | G13: =IF(B13=0," ",E13*F13)
C14: =IF(B14=0," ",VLOOKUP(A14,'US industry averages'!$A$2:$I$95,9)) | D14: =IF(B14=0," ",B14*C14) | E14: =IF(B14=0," ",D14/$D$21) | F14: =IF(B14=0," ",VLOOKUP(A14,'US industry averages'!$A$2:$I$95,8)) | G14: =IF(B14=0," ",E14*F14)
C15: =IF(B15=0," ",VLOOKUP(A15,'US industry averages'!$A$2:$I$95,9)) | D15: =IF(B15=0," ",B15*C15) | E15: =IF(B15=0," ",D15/$D$21) | F15: =IF(B15=0," ",VLOOKUP(A15,'US industry averages'!$A$2:$I$95,8)) | G15: =IF(B15=0," ",E15*F15)
C16: =IF(B16=0," ",VLOOKUP(A16,'US industry averages'!$A$2:$I$95,9)) | D16: =IF(B16=0," ",B16*C16) | E16: =IF(B16=0," ",D16/$D$21) | F16: =IF(B16=0," ",VLOOKUP(A16,'US industry averages'!$A$2:$I$95,8)) | G16: =IF(B16=0," ",E16*F16)
C17: =IF(B17=0," ",VLOOKUP(A17,'US industry averages'!$A$2:$I$95,9)) | D17: =IF(B17=0," ",B17*C17) | E17: =IF(B17=0," ",D17/$D$21) | F17: =IF(B17=0," ",VLOOKUP(A17,'US industry averages'!$A$2:$I$95,8)) | G17: =IF(B17=0," ",E17*F17)
C18: =IF(B18=0," ",VLOOKUP(A18,'US industry averages'!$A$2:$I$95,9)) | D18: =IF(B18=0," ",B18*C18) | E18: =IF(B18=0," ",D18/$D$21) | F18: =IF(B18=0," ",VLOOKUP(A18,'US industry averages'!$A$2:$I$95,8)) | G18: =IF(B18=0," ",E18*F18)
C19: =IF(B19=0," ",VLOOKUP(A19,'US industry averages'!$A$2:$I$95,9)) | D19: =IF(B19=0," ",B19*C19) | E19: =IF(B19=0," ",D19/$D$21) | F19: =IF(B19=0," ",VLOOKUP(A19,'US industry averages'!$A$2:$I$95,8)) | G19: =IF(B19=0," ",E19*F19)
C20: =IF(B20=0," ",VLOOKUP(A20,'US industry averages'!$A$2:$I$95,9)) | D20: =IF(B20=0," ",B20*C20) | E20: =IF(B20=0," ",D20/$D$21) | F20: =IF(B20=0," ",VLOOKUP(A20,'US industry averages'!$A$2:$I$95,8)) | G20: =IF(B20=0," ",E20*F20)
A21: Total operating businesses | B21: =SUM(B3:B20) -> 58235 | D21: =SUM(D3:D20) -> 102584.59 | E21: =SUM(E3:E7) -> 1 | G21: =SUM(G3:G20) -> 1.085442
A23: Other inputs
A24: Cash | B24: 4819
A25: Total Debt | B25: ='Market value of debt'!$B$7 -> 24019.941 | C25: (See worksheet for converting book value of interest bearing debt to market value)
A26: PV of lease commitments | B26: ='Lease conversion'!C34 -> 2265.0253 | C26: ( See worksheet for converting leases)
A27: Market capitalization | B27: 84050
A28: Marginal tax rate | B28: 0.24 | C28: (See worksheet for marginal tax rate, by country)
A30: Unlevered beta for operating assets = | B30: =G21 -> 1.085442
A31: Unlevered beta for company = | B31: =G21*D21/(D21+B24)+0*(B24/(B24+D21)) -> 1.0367402
A33: D/E ratio = | B33: =(B25+B26)/B27 -> 0.31273012
A34: Levered beta for operating assets = | B34: =B30*(1+(1-B28)*B33) -> 1.3434243 | C34: This is the beta to use in your cost of capital computation. Cost of capital applies only to operating assets.
A35: Levered beta for company = | B35: =B31*(1+(1-0.4)*B33) -> 1.2312722 | C35: This is the beta to use if you want a cost of equity for your entire firm.
C36: You may use this to compare to an overall return on equity or to discount any cashflow that includes interest income in it.

Sheet US industry averages
A1: Industry Name | B1: Number of firms | C1: Beta | D1: D/E Ratio | E1: Effective Tax rate | F1: Unlevered beta | G1: Cash/Firm value | H1: Unlevered beta corrected for cash | I1: EV/Sales
A2: Industry Name | B2: Number of firms | C2: Beta | D2: D/E Ratio | E2: Effective Tax rate | F2: Unlevered beta | G2: Cash/Firm value | H2: Unlevered beta corrected for cash | I2: EV/Sales
A3: Advertising | B3: 58 | C3: 1.6317381 | D3: 0.44988945 | E3: 0.063905088 | F3: 1.2200667 | G3: 0.093488854 | H3: 1.3458927 | I3: 1.9623441
A4: Aerospace/Defense | B4: 77 | C4: 1.4141823 | D4: 0.26057121 | E4: 0.086027664 | F4: 1.182992 | G4: 0.037667224 | H4: 1.2292962 | I4: 2.5451076
A5: Air Transport | B5: 21 | C5: 1.4159651 | D5: 1.8633437 | E5: 0.10471813 | F5: 0.59059874 | G5: 0.14899071 | H5: 0.693998 | I5: 1.0151711
A6: Apparel | B6: 39 | C6: 1.3246974 | D6: 0.51572352 | E6: 0.12038118 | F6: 0.95522385 | G6: 0.060170318 | H6: 1.0163797 | I6: 1.1592906
A7: Auto & Truck | B7: 31 | C7: 1.5405977 | D7: 0.50190984 | E7: 0.029973505 | F7: 1.1192687 | G7: 0.086707774 | H7: 1.2255318 | I7: 1.8115111
A8: Auto Parts | B8: 37 | C8: 1.4739918 | D8: 0.42655404 | E8: 0.092966768 | F8: 1.1167319 | G8: 0.071275727 | H8: 1.2024365 | I8: 0.82277243
A9: Bank (Money Center) | B9: 7 | C9: 1.0801016 | D9: 2.1638477 | E9: 0.16253159 | F9: 0.41179894 | G9: 0.44301926 | H9: 0.73934143 | I9: 4.4949346
A10: Banks (Regional) | B10: 557 | C10: 0.50487423 | D10: 0.64619811 | E10: 0.18838463 | F10: 0.34006312 | G10: 0.176564 | H10: 0.41298064 | I10: 4.3436213
A11: Beverage (Alcoholic) | B11: 23 | C11: 1.0129742 | D11: 0.22909688 | E11: 0.093937842 | F11: 0.86444329 | G11: 0.018550559 | H11: 0.88078229 | I11: 4.0713428
A12: Beverage (Soft) | B12: 31 | C12: 1.3034433 | D12: 0.15269045 | E12: 0.064164664 | F12: 1.1695132 | G12: 0.026552309 | H12: 1.2014135 | I12: 4.6668573
A13: Broadcasting | B13: 26 | C13: 1.3220586 | D13: 1.4683208 | E13: 0.15763232 | F13: 0.62918005 | G13: 0.10393631 | H13: 0.70215996 | I13: 1.3273528
A14: Brokerage & Investment Banking | B14: 30 | C14: 1.2048083 | D14: 2.0108832 | E14: 0.15316532 | F14: 0.48035498 | G14: 0.30759698 | H14: 0.69375056 | I14: 4.4584614
... A96: Utility (Water) | B96: 16 | C96: 1.1524154 | D96: 0.43396476 | E96: 0.084454308 | F96: 0.86943669 | G96: 0.0035347975 | H96: 0.87252088 | I96: 9.1829446

Sheet Market value of debt
B1: Inputs
A2: Book value of debt | B2: 23221
A3: Interest expense | B3: 893 | C3: (Gross interest expense, if you can get it)
A4: Average maturity | B4: 12.45
A5: Pre-tax cost of debt | B5: 0.035
D6: Book interest rate = | E6: =B3/B2 -> 0.038456569
A7: Estimated market value of debt | B7: =B3*(1-(1+B5)^-B4)/B5+B2/(1+B5)^B4 -> 24019.941

Sheet Lease conversion
A1: Operating Lease Converter
A2: Operating lease expenses are really financial expenses, and should be treated as such. Accounting standards allow them to
A3: be treated as operating expenses. This program will convert commitments to make operating leases into debt and
A4: adjust the operating income accordingly, by adding back the imputed interest expense on this debt.
A6: Inputs
A7: Operating lease expense in current year = | E7: 646
A8: Operating Lease Commitments (From footnote to financials)
A9: Year | B9: Commitment | C9: ! Year 1 is next year, ….
A10: 1 | B10: 646
A11: 2 | B11: 444
A12: 3 | B12: 444
A13: 4 | B13: 206.5
A14: 5 | B14: 206.5
A15: 6 and beyond | B15: 539
A17: Pre-tax Cost of Debt = | C17: 0.03
A19: From the current financial statements, enter the following
A20: Reported Operating Income (EBIT) = | D20: 10000 | E20: ! This is the EBIT reported in the current income statement
A21: Reported Debt = | D21: 25000 | E21: ! This is the interest-bearing debt reported on the balance sheet
A22: Reported Interest Expenses = | D22: 2000
A23: Output
A24: Number of years embedded in yr 6 estimate = | D24: =ROUND(B15/AVERAGE(B10:B14),0) -> 1 | E24: ! I use the average lease expense over the first five years
E25: to estimate the number of years of expenses in yr 6
A26: Converting Operating Leases into debt
A27: Year | B27: Commitment | C27: Present Value
A28: =A10 -> 1 | B28: =B10 -> 646 | C28: =B28/(1+$C$17)^A28 -> 627.18447
A29: =A11 -> 2 | B29: =B11 -> 444 | C29: =B29/(1+$C$17)^A29 -> 418.51258
A30: =A12 -> 3 | B30: =B12 -> 444 | C30: =B30/(1+$C$17)^A30 -> 406.3229
A31: =A13 -> 4 | B31: =B13 -> 206.5 | C31: =B31/(1+$C$17)^A31 -> 183.47258
A32: =A14 -> 5 | B32: =B14 -> 206.5 | C32: =B32/(1+$C$17)^A32 -> 178.12871
A33: =A15 -> 6 and beyond | B33: =IF(B15>0,IF(D24>1,B15/D24,B15),0) -> 539 | C33: =IF(D24>0,(B33*(1-(1+C17)^(-D24))/C17)/(1+$C$17)^5,B33/(1+C17)^6) -> 451.40401 | D33: ! Commitment beyond year 6 converted into an annuity for ten years
A34: Debt Value of leases = | C34: =SUM(C28:C33) -> 2265.0253

Sheet Marginal tax rate
A1: Country | B1: Tax Rate 2020
A2: Afghanistan | B2: 0.2
A3: Albania | B3: 0.15
A4: Algeria | B4: 0.26
A5: Andorra | B5: 0.1
A6: Angola | B6: 0.3
A7: Anguilla | B7: 0
A8: Antigua and Barbuda | B8: 0.25
A9: Argentina | B9: 0.3
A10: Armenia | B10: 0.18
A11: Aruba | B11: 0.25
A12: Australia | B12: 0.3
A13: Austria | B13: 0.25
... A184: South America average | B184: 0.2736
